Metadata-Version: 2.1
Name: git-fast-import-merge
Version: 1.0.1321
Summary: Offline merge for git fast-import files
Home-page: https://github.com/gdraheim/git_fast_import_merge
Author: Guido U. Draheim
Author-email: Guido.Draheim@gmx.de
License: APL
Platform: UNKNOWN
